mcrcon_ipv6/__init__.py
mcrcon_ipv6/mcrcon.py
mcrcon_ipv6-0.1.3.dist-info/LICENSE
mcrcon_ipv6-0.1.3.dist-info/WHEEL
mcrcon_ipv6-0.1.3.dist-info/METADATA
mcrcon_ipv6-0.1.3.dist-info/RECORD
