Metadata-Version: 2.1
Name: mcrcon-ipv6
Version: 0.1.3
Summary: mcrcon with IPv6 support
Home-page: https://github.com/fire-squad/mcrcon
License: AGPL3
Author: firesquare
Author-email: team@firesquare.ru
Requires-Python: >=3.8,<4.0
Classifier: License :: Other/Proprietary License
Classifier: Programming Language :: Python :: 3
Classifier: Programming Language :: Python :: 3.10
Classifier: Programming Language :: Python :: 3.8
Classifier: Programming Language :: Python :: 3.9
Project-URL: Repository, https://github.com/fire-squad/mcrcon
